<DOMSymbolItem xmlns:xsi="http://www.w3.org/2001/XMLSchema-instance" xmlns="http://ns.adobe.com/xfl/2008/" name="main_menu/panel_lines/line_popup/gr_arrowpos_1" itemID="4e5388c4-0000061b" lastModified="1314872771">
  <timeline>
    <DOMTimeline name="gr_arrowpos_1">
      <layers>
        <DOMLayer name="Layer 2" color="#9933CC" current="true" isSelected="true">
          <frames>
            <DOMFrame index="0" keyMode="9728">
              <elements>
                <DOMShape>
                  <fills>
                    <FillStyle index="1">
                      <SolidColor/>
                    </FillStyle>
                  </fills>
                  <edges>
                    <Edge fillStyle1="1" edges="!1400 40S2|0 40!0 40|0 0!0 0|1400 0!1400 0|1400 -60!1400 -60|1600 20!1600 20|1400 100!1400 100|1400 40"/>
                  </edges>
                </DOMShape>
              </elements>
            </DOMFrame>
          </frames>
        </DOMLayer>
      </layers>
    </DOMTimeline>
  </timeline>
</DOMSymbolItem>