<DOMSymbolItem xmlns:xsi="http://www.w3.org/2001/XMLSchema-instance" xmlns="http://ns.adobe.com/xfl/2008/" name="controls/video_player/btnVideoPause" itemID="57c022ba-00000282" symbolType="button" lastModified="1472416819">
  <timeline>
    <DOMTimeline name="btnVideoPause">
      <layers>
        <DOMLayer name="highlight2" color="#9933CC" locked="true" autoNamed="false">
          <frames>
            <DOMFrame index="0" duration="2" keyMode="9728">
              <elements/>
            </DOMFrame>
            <DOMFrame index="2" duration="2" keyMode="9728">
              <elements>
                <DOMShape>
                  <fills>
                    <FillStyle index="1">
                      <SolidColor color="#66FFFF" alpha="0.203921568627451"/>
                    </FillStyle>
                  </fills>
                  <edges>
                    <Edge fillStyle1="1" edges="!0 0S2|460 0!460 0|460 460!460 460|0 460!0 460|0 0"/>
                  </edges>
                </DOMShape>
              </elements>
            </DOMFrame>
          </frames>
        </DOMLayer>
        <DOMLayer name="Layer 5" color="#009999" locked="true">
          <frames>
            <DOMFrame index="0" duration="4" keyMode="9728">
              <elements>
                <DOMShape>
                  <fills>
                    <FillStyle index="1">
                      <SolidColor/>
                    </FillStyle>
                  </fills>
                  <edges>
                    <Edge fillStyle1="1" edges="!110 110|202 110!202 110|202 350!202 350|110 350!110 350|110 110!258 110|350 110!350 110|350 350!350 350|258 350!258 350|258 110"/>
                  </edges>
                </DOMShape>
              </elements>
            </DOMFrame>
          </frames>
        </DOMLayer>
        <DOMLayer name="Layer 4" color="#FF4FFF">
          <frames>
            <DOMFrame index="0" duration="4" keyMode="9728">
              <elements>
                <DOMShape>
                  <fills>
                    <FillStyle index="1">
                      <SolidColor color="#FFFFFF"/>
                    </FillStyle>
                  </fills>
                  <edges>
                    <Edge fillStyle1="1" edges="!110 130|202 130!202 130|202 370!202 370|110 370!110 370|110 130!258 130|350 130!350 130|350 370!350 370|258 370!258 370|258 130"/>
                  </edges>
                </DOMShape>
              </elements>
            </DOMFrame>
          </frames>
        </DOMLayer>
        <DOMLayer name="background" color="#4FFFFF" locked="true" current="true" isSelected="true" autoNamed="false">
          <frames>
            <DOMFrame index="0" keyMode="9728">
              <elements>
                <DOMShape>
                  <fills>
                    <FillStyle index="1">
                      <LinearGradient>
                        <matrix>
                          <Matrix a="0" b="-0.013427734375" c="-0.013427734375" d="0" tx="11.5" ty="11.5"/>
                        </matrix>
                        <GradientEntry color="#E5E5E5" ratio="0"/>
                        <GradientEntry color="#FFFFFF" ratio="1"/>
                      </LinearGradient>
                    </FillStyle>
                  </fills>
                  <strokes>
                    <StrokeStyle index="1">
                      <SolidStroke scaleMode="normal" caps="none" joints="miter" miterLimit="4">
                        <fill>
                          <SolidColor color="#B2B2B2"/>
                        </fill>
                      </SolidStroke>
                    </StrokeStyle>
                  </strokes>
                  <edges>
                    <Edge fillStyle1="1" strokeStyle="1" edges="!10 10|450 10!450 10|450 450!450 450|10 450!10 450|10 10"/>
                    <Edge cubics="!450 450(;450,450 10,450 10,450q450 450 10 450);"/>
                    <Edge cubics="!10 450(;10,450 10,10 10,10q10 450 10 10);"/>
                    <Edge cubics="!10 10(;10,10 450,10 450,10q10 10 450 10);"/>
                    <Edge cubics="!450 10(;450,10 450,450 450,450q450 10 450 450);"/>
                  </edges>
                </DOMShape>
                <DOMGroup>
                  <members/>
                </DOMGroup>
              </elements>
            </DOMFrame>
            <DOMFrame index="1" keyMode="9728">
              <elements>
                <DOMShape>
                  <fills>
                    <FillStyle index="1">
                      <LinearGradient>
                        <matrix>
                          <Matrix a="0" b="-0.013427734375" c="-0.013427734375" d="0" tx="11.5" ty="11.5"/>
                        </matrix>
                        <GradientEntry color="#99D7FE" ratio="0"/>
                        <GradientEntry color="#D9F0FE" ratio="1"/>
                      </LinearGradient>
                    </FillStyle>
                  </fills>
                  <strokes>
                    <StrokeStyle index="1">
                      <SolidStroke scaleMode="normal" caps="none" joints="miter" miterLimit="4">
                        <fill>
                          <LinearGradient>
                            <matrix>
                              <Matrix a="0.0140380859375" d="0.0140380859375" tx="11.5" ty="11.5"/>
                            </matrix>
                            <GradientEntry color="#0075BF" ratio="0"/>
                            <GradientEntry color="#009DFF" ratio="0.992156862745098"/>
                          </LinearGradient>
                        </fill>
                      </SolidStroke>
                    </StrokeStyle>
                  </strokes>
                  <edges>
                    <Edge fillStyle1="1" strokeStyle="1" edges="!10 10S6|450 10!450 10|450 450!450 450|10 450!10 450|10 10"/>
                    <Edge cubics="!450 450(;450,450 10,450 10,450q450 450 10 450);"/>
                    <Edge cubics="!10 450(;10,450 10,10 10,10q10 450 10 10);"/>
                    <Edge cubics="!10 10(;10,10 450,10 450,10q10 10 450 10);"/>
                    <Edge cubics="!450 10(;450,10 450,450 450,450q450 10 450 450);"/>
                  </edges>
                </DOMShape>
                <DOMGroup>
                  <members/>
                </DOMGroup>
              </elements>
            </DOMFrame>
            <DOMFrame index="2" duration="2" keyMode="9728">
              <elements>
                <DOMShape>
                  <fills>
                    <FillStyle index="1">
                      <LinearGradient>
                        <matrix>
                          <Matrix a="0" b="0.013427734375" c="0.013427734375" d="0" tx="11.5" ty="11.5"/>
                        </matrix>
                        <GradientEntry color="#99D7FE" ratio="0"/>
                        <GradientEntry color="#D9F0FE" ratio="1"/>
                      </LinearGradient>
                    </FillStyle>
                  </fills>
                  <strokes>
                    <StrokeStyle index="1">
                      <SolidStroke scaleMode="normal" caps="none" joints="miter" miterLimit="4">
                        <fill>
                          <LinearGradient>
                            <matrix>
                              <Matrix a="0.0140380859375" d="0.0140380859375" tx="11.5" ty="11.5"/>
                            </matrix>
                            <GradientEntry color="#0075BF" ratio="0"/>
                            <GradientEntry color="#009DFF" ratio="0.992156862745098"/>
                          </LinearGradient>
                        </fill>
                      </SolidStroke>
                    </StrokeStyle>
                  </strokes>
                  <edges>
                    <Edge fillStyle1="1" strokeStyle="1" edges="!450 10S6|450 450!450 450|10 450!10 450|10 10!10 10|450 10"/>
                    <Edge cubics="!450 450(;450,450 10,450 10,450q450 450 10 450);"/>
                    <Edge cubics="!10 450(;10,450 10,10 10,10q10 450 10 10);"/>
                    <Edge cubics="!10 10(;10,10 450,10 450,10q10 10 450 10);"/>
                    <Edge cubics="!450 10(;450,10 450,450 450,450q450 10 450 450);"/>
                  </edges>
                </DOMShape>
                <DOMGroup>
                  <members/>
                </DOMGroup>
              </elements>
            </DOMFrame>
          </frames>
        </DOMLayer>
      </layers>
    </DOMTimeline>
  </timeline>
</DOMSymbolItem>